mlopx/__init__.py
mlopx/requirements.txt
mlopx/pipelines/__init__.py
mlopx/pipelines/artifacts.py
mlopx/pipelines/component.py
mlopx/pipelines/component_converter.py
mlopx/pipelines/consts.py
mlopx/pipelines/pipeline.py
mlopx/pipelines/pipeline_builder.py
mlopx/utils/__init__.py
mlopx/utils/json_encoder.py
mlopx/utils/model_details.py
mlopx-1.0.8.dist-info/METADATA
mlopx-1.0.8.dist-info/WHEEL
mlopx-1.0.8.dist-info/RECORD
